src/2023/guia6/pc_module/pc_module.v
module pc_module(
    input wire clk,
    input wire [15:0] pcNext,
    output reg [15:0] pc
);

    always @(posedge clk) begin
        pc <= pcNext;
    end

endmodule

src/2023/guia6/pc_module/pc_module_tb.v
module pc_module_tb;

    reg clk;
    reg [15:0] pcNext;
    wire [15:0] pc;
    
    // Instancia del módulo a probar
    pc_module uut (
        .clk(clk),
        .pcNext(pcNext),
        .pc(pc)
    );
    // Ciclo de reloj
  
    always #5 clk = ~clk;

    // Generación de señales de prueba
    initial begin

        $dumpfile("pc_module_tb.vcd");
        $dumpvars(0, pc_module_tb);

        clk = 0;
        pcNext = 0;

        // Estímulo de prueba
        // Inicialización
        #10 pcNext = 16'h0000; // Establecer un nuevo valor para pcNext
        #20 pcNext = 16'h0001;
        #30 pcNext = 16'h1234;
        #40 pcNext = 16'hABCD;

        #100 $finish; // Terminar la simulación después de cierto tiempo
    end

endmodule

src/2023/guia6/pc_module/pc_module_tb.vcd
$date
	Sat Nov 11 13:02:11 2023
$end
$version
	Icarus Verilog
$end
$timescale
	1ps
$end
$scope module pc_module_tb $end
$var wire 16 ! pc [15:0] $end
$var reg 1 " clk $end
$var reg 16 # pcNext [15:0] $end
$scope module uut $end
$var wire 1 " clk $end
$var wire 16 $ pcNext [15:0] $end
$var reg 16 % pc [15:0] $end
$upscope $end
$upscope $end
$enddefinitions $end
#0
$dumpvars
bx %
b0 $
b0 #
0"
bx !
$end
#5
b0 !
b0 %
1"
#10
0"
#15
1"
#20
0"
#25
1"
#30
0"
b1 #
b1 $
#35
b1 !
b1 %
1"
#40
0"
#45
1"
#50
0"
#55
1"
#60
0"
b1001000110100 #
b1001000110100 $
#65
b1001000110100 !
b1001000110100 %
1"
#70
0"
#75
1"
#80
0"
#85
1"
#90
0"
#95
1"
#100
0"
b1010101111001101 #
b1010101111001101 $
#105
b1010101111001101 !
b1010101111001101 %
1"
